<?xml version = "1.0" encoding ="utf-8"?>
<node>
<id>00001</id>
<name>사과</name>
<quantity>100</quantity>
<expiration>2014-06-11</expiration>
<id>00002</id>
<name>감</name>
<quantity>496</quantity>
<expiration>2013-12-11</expiration>
<id>00003</id>
<name>귤</name>
<quantity>996</quantity>
<expiration>2013-12-28</expiration>
<id>00004</id>
<name>복숭아</name>
<quantity>800</quantity>
<expiration>2013-12-28</expiration>
<id>00005</id>
<name>딸기</name>
<quantity>150</quantity>
<expiration>2014-01-28</expiration>
<id>00006</id>
<name>오렌지</name>
<quantity>1980</quantity>
<expiration>2014-09-14</expiration>
<id>00007</id>
<name>블루베리</name>
<quantity>3000</quantity>
<expiration>2013-11-27</expiration>
<id>00008</id>
<name>월소주</name>
<quantity>200</quantity>
<expiration>2013-11-21</expiration>
<id>00009</id>
<name>C1소주</name>
<quantity>197</quantity>
<expiration>2014-05-20</expiration>
<id>00010</id>
<name>참이슬</name>
<quantity>1250</quantity>
<expiration>2014-05-01</expiration>
<id>00011</id>
<name>처음처럼</name>
<quantity>700</quantity>
<expiration>2014-03-12</expiration>
<id>00012</id>
<name>참</name>
<quantity>300</quantity>
<expiration>2013-11-12</expiration>
<id>00013</id>
<name>잎새주</name>
<quantity>175</quantity>
<expiration>2013-12-12</expiration>
<id>00014</id>
<name>시원한청풍</name>
<quantity>125</quantity>
<expiration>2014-05-01</expiration>
<id>00015</id>
<name>즐겨찾기</name>
<quantity>199</quantity>
<expiration>2014-04-07</expiration>
<id>00016</id>
<name>하이트</name>
<quantity>1009</quantity>
<expiration>2014-03-03</expiration>
<id>00017</id>
<name>마망</name>
<quantity>200</quantity>
<expiration>2016-06-01</expiration>
<id>00018</id>
<name>팸퍼스</name>
<quantity>300</quantity>
<expiration>2016-03-19</expiration>
<id>00019</id>
<name>하기스</name>
<quantity>2000</quantity>
<expiration>2016-04-19</expiration>
<id>00020</id>
<name>보솜이</name>
<quantity>650</quantity>
<expiration>2014-08-25</expiration>
<id>00021</id>
<name>마이포코</name>
<quantity>204</quantity>
<expiration>2013-08-25</expiration>
<id>00022</id>
<name>민우</name>
<quantity>30</quantity>
<expiration>2014-02-22</expiration>
<id>00043</id>
<name>신라면</name>
<quantity>400</quantity>
<expiration>2014-05-07</expiration>
</node>
